odoo10_addon_account_move_reconcile_helper-10.0.1.0.0-py2.7-nspkg.pth
odoo/addons/account_move_reconcile_helper/README.rst
odoo/addons/account_move_reconcile_helper/__init__.py
odoo/addons/account_move_reconcile_helper/__manifest__.py
odoo/addons/account_move_reconcile_helper/models/__init__.py
odoo/addons/account_move_reconcile_helper/models/account_move_line.py
odoo/addons/account_move_reconcile_helper/static/description/icon.png
odoo/addons/account_move_reconcile_helper/static/docs/journal_entries_1.png
odoo/addons/account_move_reconcile_helper/static/docs/journal_entries_2.png
odoo/addons/account_move_reconcile_helper/tests/__init__.py
odoo/addons/account_move_reconcile_helper/tests/test_account_move_reconcile_helper.py
odoo/addons/account_move_reconcile_helper/views/account_move_line.xml
odoo10_addon_account_move_reconcile_helper-10.0.1.0.0.dist-info/DESCRIPTION.rst
odoo10_addon_account_move_reconcile_helper-10.0.1.0.0.dist-info/METADATA
odoo10_addon_account_move_reconcile_helper-10.0.1.0.0.dist-info/RECORD
odoo10_addon_account_move_reconcile_helper-10.0.1.0.0.dist-info/WHEEL
odoo10_addon_account_move_reconcile_helper-10.0.1.0.0.dist-info/metadata.json
odoo10_addon_account_move_reconcile_helper-10.0.1.0.0.dist-info/namespace_packages.txt
odoo10_addon_account_move_reconcile_helper-10.0.1.0.0.dist-info/top_level.txt
